[
  {
    "id": 1,
    "typ": "bunda",
    "barva": ["cerna"],
    "odstin": "tmava",
    "vzor": null,
    "material": null,
    "styl": ["casual"],
    "sezona": ["zima"],
    "delka": "stredni",
    "strih": "volny",
    "img": "bunda_cerna_zimni.jpg"
  },
  {
    "id": 2,
    "typ": "bunda",
    "barva": ["cerna"],
    "odstin": "tmava",
    "vzor": null,
    "material": null,
    "styl": ["casual"],
    "sezona": ["jaro, podzim, leto", "podzim"],
    "delka": "kratka",
    "strih": "regular",
    "img": "bunda_cerna.jpg"
  },
  {
    "id": 3,
    "typ": "bunda",
    "barva": ["bila"],
    "odstin": "svetly",
    "vzor": null,
    "material": "denim",
    "styl": ["casual"],
    "sezona": ["jaro", "podzim", "leto"],
    "delka": "kratka",
    "strih": "regular",
    "img": "bunda_denim_bila.jpg"
  },
  {
    "id": 4,
    "typ": "bunda",
    "barva": ["cervena", "vinova"],
    "odstin": "tmavy",
    "vzor": null,
    "material": "kuze",
    "styl": ["casual"],
    "sezona": ["jaro", "podzim"],
    "delka": "kratka",
    "strih": "slim",
    "img": "bunda_kozena_tmcervena.jpg"
  },
  {
    "id": 5,
    "typ": "bunda",
    "barva": ["cerna"],
    "odstin": "tmava",
    "vzor": null,
    "material": "kuze",
    "styl": ["casual"],
    "sezona": ["jaro", "podzim"],
    "delka": "kratka",
    "strih": "slim",
    "img": "bunda_kozena.jpg"
  },
  {
    "id": 6,
    "typ": "bunda",
    "barva": ["bezova"],
    "odstin": "svetly",
    "vzor": null,
    "material": "mansestr",
    "styl": ["casual"],
    "sezona": ["jaro", "podzim"],
    "delka": "kratka",
    "strih": "regular",
    "img": "bunda_mansestr_bezova.jpg"
  },
  {
    "id": 7,
    "typ": "bunda",
    "barva": ["khaki"],
    "odstin": "tmavy",
    "vzor": null,
    "material": null,
    "styl": ["casual"],
    "sezona": ["podzim"],
    "delka": "kratka",
    "strih": "regular",
    "img": "bunda_prosivana.jpg"
  },
  {
    "id": 8,
    "typ": "bunda",
    "barva": ["cerna"],
    "odstin": "tmava",
    "vzor": null,
    "material": null,
    "styl": ["sportovni"],
    "sezona": ["jaro", "podzim"],
    "delka": "stredni",
    "strih": "regular",
    "img": "bunda_sportovni.jpg"
  },
  {
    "id": 9,
    "typ": "bunda",
    "barva": ["ruzova"],
    "odstin": "svetly",
    "vzor": null,
    "material": null,
    "styl": ["casual"],
    "sezona": ["jaro"],
    "delka": "kratka",
    "strih": "regular",
    "img": "bunda_svruzova.jpg"
  },
  {
    "id": 10,
    "typ": "bunda",
    "barva": ["zelena", "khaki"],
    "odstin": "tmavy",
    "vzor": null,
    "material": null,
    "styl": ["casual"],
    "sezona": ["zima"],
    "delka": "dlouha",
    "strih": "volny",
    "img": "bunda_zimni_zelena.jpg"
  },
  {
    "id": 11,
    "typ": "bunda",
    "barva": ["cerna"],
    "odstin": null,
    "vzor": null,
    "material": null,
    "styl": ["sportovni"],
    "sezona": ["zima"],
    "delka": "dlouha",
    "strih": "volne",
    "img": "bunda_zimni_zelena.jpg"
  },
  {
    "id": 12,
    "typ": "bunda",
    "barva": ["cerna"],
    "odstin": "tmava",
    "vzor": null,
    "material": null,
    "styl": ["casual"],
    "sezona": ["jaro", "podzim"],
    "delka": "dlouha",
    "strih": "volne",
    "img": "parka_dlouha_cerna.jpg"
  },
  {
    "id": 13,
    "typ": "bunda",
    "barva": ["zluta"],
    "odstin": "svetly",
    "vzor": null,
    "material": null,
    "styl": ["casual"],
    "sezona": ["jaro"],
    "delka": "dlouha",
    "strih": "volne",
    "img": "parka_zelena.jpg"
  },
  {
    "id": 14,
    "typ": "halenka",
    "barva": ["bila"],
    "odstin": "svetly",
    "vzor": null,
    "material": null,
    "styl": ["casual"],
    "sezona": ["jaro", "leto"],
    "delka": "kratka",
    "strih": "regular",
    "img": "halenka_bila_3_4.jpg"
  },
  {
    "id": 15,
    "typ": "halenka",
    "barva": ["bila"],
    "odstin": "svetly",
    "vzor": null,
    "material": "bavlna",
    "styl": ["casual"],
    "sezona": ["jaro", "leto"],
    "delka": "kratka",
    "strih": "regular",
    "img": "halenka_bila.jpg"
  },
  {
    "id": 16,
    "typ": "halenka",
    "barva": ["cervena", "bordo"],
    "odstin": "tmavy",
    "vzor": "kvetovane",
    "material": "bavlna",
    "styl": ["casual"],
    "sezona": ["jaro", "leto", "podzim"],
    "delka": "kratka",
    "strih": "regular",
    "img": "halenka_bordo.jpg"
  },
  {
    "id": 17,
    "typ": "halenka",
    "barva": ["cerna"],
    "odstin": "tmava",
    "vzor": null,
    "material": "bavlna",
    "styl": ["casual", "spolecenske"],
    "sezona": ["jaro", "leto"],
    "delka": "kratka",
    "strih": "slim",
    "img": "halenka_cerna_kratka.jpg"
  },
  {
    "id": 18,
    "typ": "halenka",
    "barva": "cerna",
    "odstin": "tmava",
    "vzor": null,
    "material": "bavlna",
    "styl": ["casual", "spolecenske"],
    "sezona": ["jaro", "leto"],
    "delka": "kratka",
    "strih": "regular",
    "img": "halenka_cerna_volan.jpg"
  },
  {
    "id": 19,
    "typ": "halenka",
    "barva": ["cerna", "bila"],
    "odstin": "tmava",
    "vzor": "puntiky",
    "material": null,
    "styl": ["casual", "spolecenske"],
    "sezona": ["jaro", "podzim"],
    "delka": "kratka",
    "strih": "regular",
    "img": "halenka_cernobila_puntiky.jpg"
  },
  {
    "id": 20,
    "typ": "halenka",
    "barva": ["cerna", "bila"],
    "odstin": "tmava",
    "vzor": "kvetinovy",
    "material": "bavlna",
    "styl": ["casual", "spolecenske"],
    "sezona": ["jaro", "leto"],
    "delka": "kratka",
    "strih": "regular",
    "img": "halenka_cernobila_vzor.jpg"
  },
  {
    "id": 21,
    "typ": "halenka",
    "barva": ["cervena"],
    "odstin": "tmavy",
    "vzor": "kvetovane",
    "material": "bavlna",
    "styl": ["casual", "spolecenske"],
    "sezona": ["jaro", "leto"],
    "delka": "kratka",
    "strih": "regular",
    "img": "halenka_cervena_azura.jpg"
  },
  {
    "id": 22,
    "typ": "halenka",
    "barva": ["zelena", "khaki"],
    "odstin": "tmavy",
    "vzor": null,
    "material": "bavlna",
    "styl": ["casual"],
    "sezona": ["jaro", "leto"],
    "delka": "kratka",
    "strih": "regular",
    "img": "halenka_khaki_muselin.jpg"
  },
  {
    "id": 23,
    "typ": "halenka",
    "barva": ["bezova"],
    "odstin": "svetly",
    "vzor": "zvireci",
    "material": "bavlna",
    "styl": ["casual"],
    "sezona": ["jaro", "leto"],
    "delka": "kratka",
    "strih": "regular",
    "img": "halenka_leopardi.jpg"
  },
  {
    "id": 24,
    "typ": "halenka",
    "barva": ["modra"],
    "odstin": "svetly",
    "vzor": null,
    "material": "len",
    "styl": ["casual", "spolecenske"],
    "sezona": ["jaro", "leto"],
    "delka": "kratka",
    "strih": "regular",
    "img": "halenka_modra_len.jpg"
  },
  {
    "id": 25,
    "typ": "halenka",
    "barva": ["modra"],
    "odstin": "svetly",
    "vzor": "pruhovane",
    "material": "bavlna",
    "styl": ["casual"],
    "sezona": ["jaro", "leto"],
    "delka": "kratka",
    "strih": "regular",
    "img": "halenka_modra_pruh.jpg"
  },
  {
    "id": 26,
    "typ": "halenka",
    "barva": ["ruzova"],
    "odstin": "svetly",
    "vzor": "kvetovane",
    "material": "krajka",
    "styl": ["casual"],
    "sezona": ["jaro", "leto"],
    "delka": "kratka",
    "strih": "regular",
    "img": "halenka_ruzova_azura.jpg"
  },
  {
    "id": 27,
    "typ": "halenka",
    "barva": ["ruzova"],
    "odstin": "svetly",
    "vzor": null,
    "material": "saten",
    "styl": ["casual", "spolecenske"],
    "sezona": ["jaro", "leto"],
    "delka": "kratka",
    "strih": "regular",
    "img": "halenka_ruzova_saten.jpg"
  },
  {
    "id": 28,
    "typ": "halenka",
    "barva": ["zelena", "bila"],
    "odstin": "svetly",
    "vzor": "kvetovane",
    "material": "bavlna",
    "styl": ["casual"],
    "sezona": ["jaro", "leto"],
    "delka": "kratka",
    "strih": "regular",
    "img": "halenka_zelenobila_vzor.jpg"
  },

  {
    "id": 29,
    "typ": "kabat",
    "barva": ["bezovy"],
    "odstin": "svetly",
    "vzor": null,
    "material": "vlna",
    "styl": ["casual"],
    "sezona": ["podzim", "zima"],
    "delka": "dlouha",
    "strih": "regular",
    "img": "kabat_bezovy.jpg"
  },
  {
    "id": 30,
    "typ": "kabat",
    "barva": ["cerna"],
    "odstin": "tmavy",
    "vzor": null,
    "material": "vlna",
    "styl": ["casual"],
    "sezona": ["podzim", "zima"],
    "delka": "stredni",
    "strih": "regular",
    "img": "kabat_cerny_kratky.jpg"
  },
  {
    "id": 31,
    "typ": "kabat",
    "barva": ["hneda"],
    "odstin": "tmavy",
    "vzor": null,
    "material": "vlna",
    "styl": ["casual"],
    "sezona": ["podzim", "zima"],
    "delka": "dlouha",
    "strih": "regular",
    "img": "kabat_hneda.jpg"
  },
  {
    "id": 32,
    "typ": "kabat",
    "barva": ["seda"],
    "odstin": "tmavy",
    "vzor": null,
    "material": "vlna",
    "styl": ["casual"],
    "sezona": ["podzim", "zima"],
    "delka": "stredni",
    "strih": "regular",
    "img": "kabat_seda_kratky.jpg"
  },
  {
    "id": 33,
    "typ": "kabat",
    "barva": ["seda"],
    "odstin": "tmavy",
    "vzor": null,
    "material": "vlna",
    "styl": ["casual"],
    "sezona": ["podzim", "zima"],
    "delka": "stredni",
    "strih": "regular",
    "img": "kabat_tmseda.jpg"
  },
  {
    "id": 34,
    "typ": "kabat",
    "barva": ["hneda"],
    "odstin": "tmavy",
    "vzor": null,
    "material": "bavlna",
    "styl": ["casual"],
    "sezona": ["podzim", "jaro"],
    "delka": "kratka",
    "strih": "regular",
    "img": "trenckot_hnedy_kratky.jpg"
  },
  {
    "id": 35,
    "typ": "kabat",
    "barva": ["bezova"],
    "odstin": "svetly",
    "vzor": null,
    "material": "bavlna",
    "styl": ["casual"],
    "sezona": ["jaro"],
    "delka": "kratka",
    "strih": "regular",
    "img": "trenckot_kratky_bezovy.jpg"
  },
  {
    "id": 36,
    "typ": "kabat",
    "barva": ["zelena"],
    "odstin": "svetly",
    "vzor": null,
    "material": "bavlna",
    "styl": ["casual"],
    "sezona": ["jaro"],
    "delka": "dlouha",
    "strih": "regular",
    "img": "trenckot_zeleny.jpg"
  },
  {
    "id": 37,
    "typ": "kabat",
    "barva": ["bezova"],
    "odstin": "svetla",
    "vzor": null,
    "material": "bavlna",
    "styl": ["casual"],
    "sezona": ["jaro", "podzim"],
    "delka": "dlouha",
    "strih": "regular",
    "img": "trenckot_bezova_dlouha.jpg"
  },

  {
    "id": 38,
    "typ": "kalhoty",
    "barva": ["modra"],
    "odstin": "svetly",
    "vzor": null,
    "material": "denim",
    "styl": ["casual"],
    "sezona": ["jaro", "podzim", "zima"],
    "delka": "dlouha",
    "strih": "regular",
    "img": "dziny.jpg"
  },
  {
    "id": 39,
    "typ": "kalhoty",
    "barva": ["bezova"],
    "odstin": "svetly",
    "vzor": null,
    "material": "bavlna",
    "styl": ["casual"],
    "sezona": ["jaro"],
    "delka": "dlouha",
    "strih": "regular",
    "img": "kalhoty_bezove.jpg"
  },
  {
    "id": 40,
    "typ": "kalhoty",
    "barva": ["bila"],
    "odstin": "svetly",
    "vzor": null,
    "material": "bavlna",
    "styl": ["formalni"],
    "sezona": ["jaro", "leto"],
    "delka": "dlouha",
    "strih": "volne",
    "img": "kalhoty_bile_fomal.jpg"
  },
  {
    "id": 41,
    "typ": "kalhoty",
    "barva": ["cerna"],
    "odstin": "tmava",
    "vzor": null,
    "material": "denim",
    "styl": ["casual"],
    "sezona": ["jaro", "podzim ", "zima"],
    "delka": "dlouha",
    "strih": "regular",
    "img": "kalhoty_cerne_denim.jpg"
  },
  {
    "id": 42,
    "typ": "kalhoty",
    "barva": ["cerna"],
    "odstin": "tmavy",
    "vzor": null,
    "material": "bavlna",
    "styl": ["formalni"],
    "sezona": ["jaro", "podzim", "leto"],
    "delka": "dlouha",
    "strih": "regular",
    "img": "kalhoty_cerne_formal.jpg"
  },
  {
    "id": 43,
    "typ": "kalhoty",
    "barva": ["seda"],
    "odstin": "svetly",
    "vzor": null,
    "material": "denim",
    "styl": ["casual"],
    "sezona": ["jaro", "podzim"],
    "delka": "dlouha",
    "strih": "regular",
    "img": "kalhoty_denim_sede.jpg"
  },
  {
    "id": 44,
    "typ": "kalhoty",
    "barva": ["moda", "bila"],
    "odstin": "svetly",
    "vzor": "kvetovane",
    "material": "krep",
    "styl": ["casual"],
    "sezona": ["jaro", "leto"],
    "delka": "dlouha",
    "strih": "regular",
    "img": "kalhoty_krep_modrobila_kvetinovy.jpg"
  },
  {
    "id": 45,
    "typ": "kalhoty",
    "barva": ["hneda"],
    "odstin": "tmavy",
    "vzor": null,
    "material": "saten",
    "styl": ["casual"],
    "sezona": ["jaro", "leto", "podzim"],
    "delka": "dlouha",
    "strih": "regular",
    "img": "kalhoty_saten_hneda.jpg"
  },
  {
    "id": 46,
    "typ": "kalhoty",
    "barva": ["zelena", "khaki"],
    "odstin": "tmavy",
    "vzor": null,
    "material": "saten",
    "styl": ["casual"],
    "sezona": ["jaro", "leto", "podzim"],
    "delka": "dlouha",
    "strih": "regular",
    "img": "kalhoty_saten_khaki.jpg"
  },
  {
    "id": 47,
    "typ": "kalhoty",
    "barva": ["seda"],
    "odstin": "svetly",
    "vzor": null,
    "material": "bavlna",
    "styl": ["casual"],
    "sezona": ["jaro", "podzim", "zima"],
    "delka": "dlouha",
    "strih": "regular",
    "img": "kalhoty_sede_formal.jpg"
  },
  {
    "id": 48,
    "typ": "kalhoty",
    "barva": ["cerna"],
    "odstin": "tmava",
    "vzor": null,
    "material": "bavlna",
    "styl": ["casual"],
    "sezona": ["jaro", "podzim"],
    "delka": "dlouha",
    "strih": "regular",
    "img": "kalhoty.jpg"
  },
  {
    "id": 49,
    "typ": "kalhoty",
    "barva": ["cerna"],
    "odstin": "tmava",
    "vzor": null,
    "material": "bavlna",
    "styl": ["casual"],
    "sezona": ["jaro", "podzim", "leto"],
    "delka": "dlouha",
    "strih": "regular",
    "img": "kalhoty.jpg"
  },
  {
    "id": 50,
    "typ": "kalhoty",
    "barva": ["hneda"],
    "odstin": "tmavy",
    "vzor": null,
    "material": "bavlna",
    "styl": ["sportovni"],
    "sezona": null,
    "delka": "dlouha",
    "strih": "regular",
    "img": "leginy_hnede_siroke.jpg"
  },
  {
    "id": 51,
    "typ": "kalhoty",
    "barva": ["khaki"],
    "odstin": "tmavy",
    "vzor": null,
    "material": "bavlna",
    "styl": ["sportovni"],
    "sezona": null,
    "delka": "stredni",
    "strih": "regular",
    "img": "leginy_khaki_3_4.jpg"
  },
  {
    "id": 52,
    "typ": "kalhoty",
    "barva": ["cerna", "bezova", "hneda"],
    "odstin": "svetly",
    "vzor": "zvireci",
    "material": "bavlna",
    "styl": ["casual"],
    "sezona": ["jaro", "leto"],
    "delka": "dlouha",
    "strih": "regular",
    "img": "leginy_ruzove.jpg"
  },
  {
    "id": 53,
    "typ": "kalhoty",
    "barva": ["hneda"],
    "odstin": "tmavy",
    "vzor": null,
    "material": "bavlna",
    "styl": ["sportovni"],
    "sezona": null,
    "delka": "dlouha",
    "strih": "regular",
    "img": "leginy.jpg"
  },

  {
    "id": 54,
    "typ": "kosile",
    "barva": ["vice barev"],
    "odstin": "svetly",
    "vzor": "kvetovane",
    "material": "bavlna",
    "styl": ["casual"],
    "sezona": ["jaro", "podzim"],
    "delka": "dlouha",
    "strih": "regular",
    "img": "kosile_bavlna_kvetovaná.jpg"
  },
  {
    "id": 55,
    "typ": "kosile",
    "barva": ["ruzova"],
    "odstin": "svetly",
    "vzor": null,
    "material": "bavlna",
    "styl": ["casual"],
    "sezona": ["jaro"],
    "delka": "dlouha",
    "strih": "regular",
    "img": "kosile_bavlna_ruzova.jpg"
  },
  {
    "id": 56,
    "typ": "kosile",
    "barva": ["bila"],
    "odstin": "svetly",
    "vzor": null,
    "material": "bavlna",
    "styl": ["formalni"],
    "sezona": ["jaro", "leto", "podzim", "zima"],
    "delka": "dlouha",
    "strih": "regular",
    "img": "kosile_bila_basic.jpg"
  },
  {
    "id": 57,
    "typ": "kosile",
    "barva": ["bila", "cervena"],
    "odstin": "svetly",
    "vzor": "pruhovane",
    "material": "bavlna",
    "styl": ["casual"],
    "sezona": ["jaro", "podzim"],
    "delka": "dlouha",
    "strih": "regular",
    "img": "kosile_bila_prouzek.jpg"
  },
  {
    "id": 58,
    "typ": "kosile",
    "barva": ["bila", "cerna"],
    "odstin": "svetly",
    "vzor": "pruhovane",
    "material": "saten",
    "styl": ["formalni"],
    "sezona": ["jaro", "podzim", "zima"],
    "delka": "dlouha",
    "strih": "regular",
    "img": "kosile_bila_pruh_saten.jpg"
  },
  {
    "id": 59,
    "typ": "kosile",
    "barva": ["seda"],
    "odstin": "svetly",
    "vzor": null,
    "material": "denim",
    "styl": ["casual"],
    "sezona": ["jaro", "podzim", "zima"],
    "delka": "dlouha",
    "strih": "regular",
    "img": "kosile_denim_seda.jpg"
  },
  {
    "id": 60,
    "typ": "kosile",
    "barva": ["bila", "kremova"],
    "odstin": "tmavy",
    "vzor": null,
    "material": "saten",
    "styl": ["formalni"],
    "sezona": ["jaro", "podzim", "zima"],
    "delka": "dlouha",
    "strih": "regular",
    "img": "kosile_kremova_saten.jpg"
  },
  {
    "id": 61,
    "typ": "kosile",
    "barva": ["bezova"],
    "odstin": "svetly",
    "vzor": null,
    "material": "bavlna",
    "styl": ["formalni"],
    "sezona": ["jaro", "podzim"],
    "delka": "dlouha",
    "strih": "regular",
    "img": "kosile_len_bezova_formalni.jpg"
  },
  {
    "id": 62,
    "typ": "kosile",
    "barva": ["zelena"],
    "odstin": "tmavy",
    "vzor": null,
    "material": "len",
    "styl": ["casual"],
    "sezona": ["jaro", "leto"],
    "delka": "kratka",
    "strih": "regular",
    "img": "kosile_len_zelena.jpg"
  },
  {
    "id": 63,
    "typ": "kosile",
    "barva": ["modra"],
    "odstin": "svetly",
    "vzor": null,
    "material": "bavlna",
    "styl": ["casual"],
    "sezona": ["jaro", "podzim"],
    "delka": "kratka",
    "strih": "regular",
    "img": "kosile_modra_bavlna.jpg"
  },
  {
    "id": 64,
    "typ": "kosile",
    "barva": ["modra", "bila"],
    "odstin": "svetly",
    "vzor": "pruhovane",
    "material": "bavlna",
    "styl": ["casual"],
    "sezona": ["jaro"],
    "delka": "kratka",
    "strih": "regular",
    "img": "kosile_svmodra_pruh.jpg"
  },

  {
    "id": 65,
    "typ": "kosile",
    "barva": ["modra"],
    "odstin": "tmava",
    "vzor": "kvetinovy",
    "material": "bavlna",
    "styl": ["casual"],
    "sezona": ["jaro"],
    "delka": "kratka",
    "strih": "regular",
    "img": "kosile_tmmodra_azura.jpg"
  },
  {
    "id": 65,
    "typ": "kosile",
    "barva": ["modra"],
    "odstin": "svetla",
    "vzor": null,
    "material": "denim",
    "styl": ["casual"],
    "sezona": ["jaro", "podzim"],
    "delka": "kratka",
    "strih": "regular",
    "img": "kosile.jpg"
  },
  {
    "id": 66,
    "typ": "kratasy",
    "barva": ["bila"],
    "odstin": "svetly",
    "vzor": "pruhovane",
    "material": "bavlna",
    "styl": ["casual"],
    "sezona": ["leto"],
    "delka": "kratka",
    "strih": "regular",
    "img": "kratasy_bavlna_pruh.jpg"
  },
  {
    "id": 67,
    "typ": "kratasy",
    "barva": ["bila"],
    "odstin": "svetly",
    "vzor": null,
    "material": "bavlna",
    "styl": ["formalni"],
    "sezona": ["leto"],
    "delka": "kratka",
    "strih": "regular",
    "img": "kratasy_bile_formal.jpg"
  },
  {
    "id": 68,
    "typ": "kratasy",
    "barva": ["bila"],
    "odstin": "svetly",
    "vzor": null,
    "material": "bavlna",
    "styl": ["formalni"],
    "sezona": ["leto"],
    "delka": "kratka",
    "strih": "regular",
    "img": "kratasy_bile_formal.jpg"
  },
  {
    "id": 69,
    "typ": "kratasy",
    "barva": ["bordo"],
    "odstin": "tmavy",
    "vzor": null,
    "material": "bavlna",
    "styl": ["casual"],
    "sezona": ["leto"],
    "delka": "kratka",
    "strih": "regular",
    "img": "kratasy_bordo.jpg"
  },
  {
    "id": 70,
    "typ": "kratasy",
    "barva": ["cerna"],
    "odstin": "tmava",
    "vzor": null,
    "material": "bavlna",
    "styl": ["casual"],
    "sezona": ["leto"],
    "delka": "kratka",
    "strih": "regular",
    "img": "kratasy_cerne_formal.jpg"
  },
  {
    "id": 71,
    "typ": "kratasy",
    "barva": ["cerna"],
    "odstin": null,
    "vzor": null,
    "material": "polyester",
    "styl": ["sportovni"],
    "sezona": null,
    "delka": "kratka",
    "strih": "slim",
    "img": "kratasy_cerne_sportovni.jpg"
  },
  {
    "id": 72,
    "typ": "kratasy",
    "barva": ["cerna"],
    "odstin": "tmava",
    "vzor": null,
    "material": "polyester",
    "styl": ["sportovni"],
    "sezona": null,
    "delka": "kratka",
    "strih": "regular",
    "img": "kratasy_cerne_sportovni.jpg"
  },
  {
    "id": 73,
    "typ": "kratasy",
    "barva": ["bila"],
    "odstin": "tmavy",
    "vzor": null,
    "material": "denim",
    "styl": ["casual"],
    "sezona": ["leto"],
    "delka": "kratka",
    "strih": "regular",
    "img": "kratasy_denim_bile.jpg"
  },
  {
    "id": 74,
    "typ": "kratasy",
    "barva": ["cerna"],
    "odstin": "tmavy",
    "vzor": null,
    "material": "denim",
    "styl": ["casual"],
    "sezona": ["leto"],
    "delka": "kratka",
    "strih": "regular",
    "img": "kratasy_denim_cerne.jpg"
  },
  {
    "id": 75,
    "typ": "kratasy",
    "barva": ["bezova"],
    "odstin": null,
    "vzor": null,
    "material": "len",
    "styl": ["casual"],
    "sezona": ["leto"],
    "delka": "kratka",
    "strih": "regular",
    "img": "kratasy_lnene_bezova.jpg"
  },
  {
    "id": 76,
    "typ": "kratasy",
    "barva": ["modra"],
    "odstin": "tmavy",
    "vzor": null,
    "material": "bavlna",
    "styl": ["casual"],
    "sezona": ["leto"],
    "delka": "kratka",
    "strih": "regular",
    "img": "kratasy_lnene_modra.jpg"
  },
  {
    "id": 77,
    "typ": "kratasy",
    "barva": ["zelena", "khaki"],
    "odstin": "tmava",
    "vzor": null,
    "material": "bavlna",
    "styl": ["sportovni"],
    "sezona": null,
    "delka": "kratka",
    "strih": "regular",
    "img": "kratasy_sportovni_zelena.jpg"
  },
  {
    "id": 78,
    "typ": "kratasy",
    "barva": ["seda"],
    "odstin": "tmavy",
    "vzor": null,
    "material": "bavlna",
    "styl": ["formalni"],
    "sezona": ["leto"],
    "delka": "kratka",
    "strih": "regular",
    "img": "kratasy_sede_formal.jpg"
  },
  {
    "id": 79,
    "typ": "kratasy",
    "barva": ["bezova"],
    "odstin": "svetly",
    "vzor": null,
    "material": "bavlna",
    "styl": ["formalni"],
    "sezona": ["leto"],
    "delka": "kratka",
    "strih": "regular",
    "img": "kratasy.jpg"
  },
  {
    "id": 80,
    "typ": "sako",
    "barva": ["bezova"],
    "odstin": "svetly",
    "vzor": null,
    "material": "bukle",
    "styl": ["formalni"],
    "sezona": ["jaro", "podzim", "leto"],
    "delka": "kratka",
    "strih": "regular",
    "img": "blejzr_kremova_bukle.jpg"
  },
  {
    "id": 81,
    "typ": "sako",
    "barva": ["cerna"],
    "odstin": "tmavy",
    "vzor": null,
    "material": "polyester",
    "styl": ["formalni", "casual"],
    "sezona": ["jaro", "podzim", "leto"],
    "delka": "kratka",
    "strih": "regular",
    "img": "sako_cerna_prilehave.jpg"
  },
  {
    "id": 82,
    "typ": "sako",
    "barva": ["cerna"],
    "odstin": "tmavy",
    "vzor": null,
    "material": "polyester",
    "styl": ["formalni", "casual"],
    "sezona": ["jaro", "podzim", "leto"],
    "delka": "dlouha",
    "strih": "regular",
    "img": "sako_cerna_delsi.jpg"
  },
  {
    "id": 83,
    "typ": "sako",
    "barva": ["cerna"],
    "odstin": "tmavy",
    "vzor": null,
    "material": "polyester",
    "styl": ["formalni", "casual"],
    "sezona": ["jaro", "podzim", "leto"],
    "delka": "kratka",
    "strih": "regular",
    "img": "sako_cerne.jpg"
  },
  {
    "id": 84,
    "typ": "sako",
    "barva": ["hneda"],
    "odstin": "tmavy",
    "vzor": "kostkovane",
    "material": "polyester",
    "styl": ["casual"],
    "sezona": ["jaro", "podzim"],
    "delka": "kratka",
    "strih": "regular",
    "img": "sako_hnede_pepito.jpg"
  },
  {
    "id": 85,
    "typ": "sako",
    "barva": ["seda"],
    "odstin": "tmavy",
    "vzor": "kostkovane",
    "material": "polyester",
    "styl": ["casual"],
    "sezona": ["jaro", "podzim"],
    "delka": "kratka",
    "strih": "regular",
    "img": "sako_kostka.jpg"
  },
  {
    "id": 86,
    "typ": "sako",
    "barva": ["bezova"],
    "odstin": "svetly",
    "vzor": null,
    "material": "krep",
    "styl": ["casual"],
    "sezona": ["jaro", "leto"],
    "delka": "kratka",
    "strih": "regular",
    "img": "sako_kremova_krep.jpg"
  },
  {
    "id": 87,
    "typ": "sako",
    "barva": ["bila"],
    "odstin": "svetly",
    "vzor": "pruhovane",
    "material": "len",
    "styl": ["casual"],
    "sezona": ["jaro", "leto"],
    "delka": "stredni",
    "strih": "regular",
    "img": "sako_lnene_pruh.jpg"
  },
  {
    "id": 88,
    "typ": "sako",
    "barva": ["modra"],
    "odstin": "svetly",
    "vzor": null,
    "material": "polyester",
    "styl": ["casual", "formalni"],
    "sezona": ["jaro", "leto"],
    "delka": "stredni",
    "strih": "regular",
    "img": "sako_svetle_modra.jpg"
  },
  {
    "id": 89,
    "typ": "sako",
    "barva": ["seda"],
    "odstin": "tmavy",
    "vzor": null,
    "material": "polyester",
    "styl": ["casual", "formalni"],
    "sezona": ["jaro", "podzim "],
    "delka": "stredni",
    "strih": "regular",
    "img": "sako_seda.jpg"
  },
  {
    "id": 90,
    "typ": "sako",
    "barva": ["modra"],
    "odstin": "tmavy",
    "vzor": null,
    "material": "polyester",
    "styl": ["casual", "formalni"],
    "sezona": ["jaro", "podzim"],
    "delka": "stredni",
    "strih": "regular",
    "img": "sako_tmave_modra.jpg"
  },
  {
    "id": 91,
    "typ": "sako",
    "barva": ["zluta"],
    "odstin": "svetly",
    "vzor": null,
    "material": "krep",
    "styl": ["casual"],
    "sezona": ["jaro", "leto"],
    "delka": "stredni",
    "strih": "regular",
    "img": "sako_zlute.jpg"
  },
  {
    "id": 92,
    "typ": "sako",
    "barva": ["hneda"],
    "odstin": "tmavy",
    "vzor": null,
    "material": "len",
    "styl": ["casual"],
    "sezona": ["leto"],
    "delka": "stredni",
    "strih": "regular",
    "img": "vesta_hneda_len.jpg"
  },
  {
    "id": 93,
    "typ": "sako",
    "barva": ["ruzova"],
    "odstin": "svetly",
    "vzor": null,
    "material": "polyester",
    "styl": ["casual"],
    "sezona": ["leto"],
    "delka": "stredni",
    "strih": "regular",
    "img": "vesta_ruzova.jpg"
  },
  {
    "id": 94,
    "typ": "sukne",
    "barva": ["bezova"],
    "odstin": "svetly",
    "vzor": null,
    "material": "denim",
    "styl": ["casual"],
    "sezona": ["jaro", "podzim", "leto"],
    "delka": "stredni",
    "strih": "regular",
    "img": "sukne_bezova_denim.jpg"
  },
  {
    "id": 95,
    "typ": "sukne",
    "barva": ["cerna"],
    "odstin": "tmavy",
    "vzor": null,
    "material": "kuze",
    "styl": ["casual"],
    "sezona": ["jaro", "podzim", "leto", "zima"],
    "delka": "kratka",
    "strih": "regular",
    "img": "sukne_cerna_kuze.jpg"
  },
  {
    "id": 96,
    "typ": "sukne",
    "barva": ["cerna"],
    "odstin": "tmavy",
    "vzor": "kvetovane",
    "material": "polyester",
    "styl": ["casual"],
    "sezona": ["jaro", "podzim", "leto"],
    "delka": "dlouha",
    "strih": "volny",
    "img": "sukne_cerna_kvetovana.jpg"
  },
  {
    "id": 97,
    "typ": "sukne",
    "barva": ["modra"],
    "odstin": "tmavy",
    "vzor": null,
    "material": "denim",
    "styl": ["casual"],
    "sezona": ["jaro", "podzim", "leto", "zima"],
    "delka": "dlouha",
    "strih": "regular",
    "img": "sukne_denim.jpg"
  },
  {
    "id": 98,
    "typ": "sukne",
    "barva": ["bila"],
    "odstin": "svetly",
    "vzor": null,
    "material": "plise",
    "styl": ["casual"],
    "sezona": ["jaro", "leto"],
    "delka": "dlouha",
    "strih": "volny",
    "img": "sukne_letni_plise_bila.jpg"
  },
  {
    "id": 99,
    "typ": "sukne",
    "barva": "ruzova",
    "odstin": "tmavy",
    "vzor": null,
    "material": "plise",
    "styl": ["casual"],
    "sezona": ["jaro", "leto"],
    "delka": "dlouha",
    "strih": "volny",
    "img": "sukne_plise_ruzova.jpg"
  },
  {
    "id": 100,
    "typ": "sukne",
    "barva": "cervena",
    "odstin": null,
    "vzor": null,
    "material": "saten",
    "styl": ["casual", "formalni"],
    "sezona": ["jaro", "leto", "podzim"],
    "delka": "dlouha",
    "strih": "regular",
    "img": "sukne_red.jpg"
  },
  {
    "id": 101,
    "typ": "sukne",
    "barva": "bila",
    "odstin": null,
    "vzor": null,
    "material": "saten",
    "styl": ["casual", "formalni"],
    "sezona": ["jaro", "leto"],
    "delka": "dlouha",
    "strih": "regular",
    "img": "sukne_saten_bila.jpg"
  },
  {
    "id": 102,
    "typ": "sukne",
    "barva": "cerna",
    "odstin": null,
    "vzor": null,
    "material": "saten",
    "styl": ["casual", "formalni"],
    "sezona": ["jaro", "leto", "podzim"],
    "delka": "dlouha",
    "strih": "regular",
    "img": "sukne_saten_cerna.jpg"
  },
  {
    "id": 103,
    "typ": "sukne",
    "barva": ["bezova", "hneda", "cerna"],
    "odstin": null,
    "vzor": null,
    "material": "saten",
    "styl": ["casual"],
    "sezona": ["jaro", "leto", "podzim"],
    "delka": "dlouha",
    "strih": "regular",
    "img": "sukne_saten_leopard.jpg"
  },
  {
    "id": 104,
    "typ": "sukne",
    "barva": ["ruzova"],
    "odstin": "svetly",
    "vzor": null,
    "material": "saten",
    "styl": ["casual"],
    "sezona": ["jaro", "leto"],
    "delka": "kratka",
    "strih": "regular",
    "img": "sukne_saten_ruzova_kratka.jpg"
  },
  {
    "id": 105,
    "typ": "sukne",
    "barva": ["seda"],
    "odstin": "tmavy",
    "vzor": null,
    "material": "saten",
    "styl": ["casual", "formalni"],
    "sezona": ["jaro", "leto", "podzim"],
    "delka": "dlouha",
    "strih": "regular",
    "img": "sukne_saten_seda.jpg"
  },
  {
    "id": 106,
    "typ": "sukne",
    "barva": ["cerna"],
    "odstin": "tmavy",
    "vzor": null,
    "material": "polyester",
    "styl": ["sportovni"],
    "sezona": ["jaro", "leto"],
    "delka": "kratka",
    "strih": "regular",
    "img": "sukne_sportovni_cerna.jpg"
  },
  {
    "id": 107,
    "typ": "sukne",
    "barva": ["zluta"],
    "odstin": "svetly",
    "vzor": null,
    "material": "sifon",
    "styl": ["casual", "formalni"],
    "sezona": ["jaro", "leto"],
    "delka": "dlouha",
    "strih": "regular",
    "img": "sukne_sifon_zluta.jpg"
  },
  {
    "id": 108,
    "typ": "sukne",
    "barva": ["zelena"],
    "odstin": "tmavy",
    "vzor": null,
    "material": "polyester",
    "styl": ["casual"],
    "sezona": ["jaro", "leto"],
    "delka": "stredni",
    "strih": "regular",
    "img": "sukne_zelena.jpg"
  },
  {
    "id": 109,
    "typ": "svetry",
    "barva": ["hneda"],
    "odstin": "tmavy",
    "vzor": null,
    "material": "vlna",
    "styl": ["casual"],
    "sezona": ["jaro", "leto", "podzim"],
    "delka": "stredni",
    "strih": "regular",
    "img": "svetr_bezova_tmava.jpg"
  },
  {
    "id": 110,
    "typ": "svetry",
    "barva": ["bezova"],
    "odstin": "svetly",
    "vzor": null,
    "material": "vlna",
    "styl": ["casual"],
    "sezona": ["jaro", "zima", "podzim"],
    "delka": "stredni",
    "strih": "regular",
    "img": "svetr_bezova.jpg"
  },
  {
    "id": 111,
    "typ": "svetry",
    "barva": ["cerna"],
    "odstin": "tmavy",
    "vzor": null,
    "material": "vlna",
    "styl": ["casual"],
    "sezona": ["jaro", "zima", "podzim"],
    "delka": "stredni",
    "strih": "regular",
    "img": "svetr_cerny_uni.jpg"
  },
  {
    "id": 112,
    "typ": "svetry",
    "barva": ["fialova"],
    "odstin": "tmavy",
    "vzor": null,
    "material": "vlna",
    "styl": ["casual"],
    "sezona": ["jaro", "zima", "podzim"],
    "delka": "stredni",
    "strih": "regular",
    "img": "svetr_fialova.jpg"
  },
  {
    "id": 113,
    "typ": "svetry",
    "barva": ["modra"],
    "odstin": "tmavy",
    "vzor": null,
    "material": "vlna",
    "styl": ["casual"],
    "sezona": ["jaro", "zima", "podzim"],
    "delka": "stredni",
    "strih": "regular",
    "img": "svetr_modra.jpg"
  },
  {
    "id": 114,
    "typ": "svetry",
    "barva": ["ruzova"],
    "odstin": "tmavy",
    "vzor": null,
    "material": "vlna",
    "styl": ["casual"],
    "sezona": ["jaro", "zima", "podzim"],
    "delka": "stredni",
    "strih": "regular",
    "img": "svetr_ruzova_tmava.jpg"
  },
  {
    "id": 115,
    "typ": "svetry",
    "barva": ["ruzova"],
    "odstin": "svetly",
    "vzor": null,
    "material": "vlna",
    "styl": ["casual"],
    "sezona": ["jaro", "zima", "podzim"],
    "delka": "stredni",
    "strih": "regular",
    "img": "svetr_ruzova.jpg"
  },
  {
    "id": 116,
    "typ": "svetry",
    "barva": ["seda"],
    "odstin": "svetly",
    "vzor": null,
    "material": "vlna",
    "styl": ["casual"],
    "sezona": ["jaro", "zima", "podzim"],
    "delka": "stredni",
    "strih": "regular",
    "img": "svetr_seda_kratky.jpg"
  },
  {
    "id": 117,
    "typ": "svetry",
    "barva": ["modra"],
    "odstin": "tmavy",
    "vzor": null,
    "material": "vlna",
    "styl": ["casual"],
    "sezona": ["jaro", "zima", "podzim"],
    "delka": "stredni",
    "strih": "regular",
    "img": "svetr_tm_modra.jpg"
  },
  {
    "id": 118,
    "typ": "svetry",
    "barva": ["bila"],
    "odstin": "svetly",
    "vzor": null,
    "material": "vlna",
    "styl": ["casual"],
    "sezona": ["jaro", "zima", "podzim", "leto"],
    "delka": "stredni",
    "strih": "slim",
    "img": "svetr_uply_pruhy.jpg"
  },
  {
    "id": 119,
    "typ": "svetry",
    "barva": ["zelena"],
    "odstin": "svetly",
    "vzor": null,
    "material": "vlna",
    "styl": ["casual"],
    "sezona": ["jaro", "zima", "podzim", "leto"],
    "delka": "stredni",
    "strih": "regular",
    "img": "svetr_zelena_svetla.jpg"
  },
  {
    "id": 120,
    "typ": "svetry",
    "barva": ["zelena"],
    "odstin": "tmavy",
    "vzor": null,
    "material": "vlna",
    "styl": ["casual"],
    "sezona": ["jaro", "zima", "podzim", "leto"],
    "delka": "stredni",
    "strih": "regular",
    "img": "svetr_zeleny_tmavy.jpg"
  },
  {
    "id": 121,
    "typ": "svetry",
    "barva": ["zluta"],
    "odstin": "svetly",
    "vzor": null,
    "material": "vlna",
    "styl": ["casual"],
    "sezona": ["jaro", "leto"],
    "delka": "stredni",
    "strih": "regular",
    "img": "svetr_zluta.jpg"
  },
  {
    "id": 122,
    "typ": "svetry",
    "barva": ["bila"],
    "odstin": "svetly",
    "vzor": null,
    "material": "vlna",
    "styl": ["casual"],
    "sezona": ["jaro", "leto"],
    "delka": "stredni",
    "strih": "regular",
    "img": "vesta_pletena_bila.jpg"
  },
  {
    "id": 123,
    "typ": "saty",
    "barva": ["cervena"],
    "odstin": "tmavy",
    "vzor": null,
    "material": "saten",
    "styl": ["casual", "formalni", "spolecenske"],
    "sezona": ["jaro", "leto", "podzim"],
    "delka": "dlouha",
    "strih": "volny",
    "img": "saty_bordo.jpg"
  },
  {
    "id": 124,
    "typ": "saty",
    "barva": ["cerna"],
    "odstin": "tmavy",
    "vzor": null,
    "material": "bavlna",
    "styl": ["casual"],
    "sezona": ["jaro", "leto"],
    "delka": "stredni",
    "strih": "volne",
    "img": "saty_cerne_balon.jpg"
  },
  {
    "id": 125,
    "typ": "saty",
    "barva": ["cerna"],
    "odstin": "tmavy",
    "vzor": null,
    "material": "polyester",
    "styl": ["formalni"],
    "sezona": ["jaro", "leto"],
    "delka": "stredni",
    "strih": "regular",
    "img": "saty_cerne_formal.jpg"
  },
  {
    "id": 126,
    "typ": "saty",
    "barva": ["cerna"],
    "odstin": "tmavy",
    "vzor": null,
    "material": "polyester",
    "styl": ["casual"],
    "sezona": ["leto"],
    "delka": "kratka",
    "strih": "regular",
    "img": "saty_cerne_mini.jpg"
  },
  {
    "id": 127,
    "typ": "saty",
    "barva": ["modra"],
    "odstin": "tmavy",
    "vzor": null,
    "material": "krep",
    "styl": ["casual"],
    "sezona": ["leto"],
    "delka": "dlouha",
    "strih": "volny",
    "img": "saty_krep_modre.jpg"
  },
  {
    "id": 128,
    "typ": "saty",
    "barva": ["bila"],
    "odstin": "svetly",
    "vzor": null,
    "material": "len",
    "styl": ["casual"],
    "sezona": ["leto"],
    "delka": "dlouha",
    "strih": "volny",
    "img": "saty_len_pruh.jpg"
  },
  {
    "id": 129,
    "typ": "saty",
    "barva": ["bila", "cerna"],
    "odstin": "svetly",
    "vzor": null,
    "material": "bavlna",
    "styl": ["casual"],
    "sezona": ["jaro", "podzim"],
    "delka": "dlouha",
    "strih": "regular",
    "img": "saty_pruh.jpg"
  },
  {
    "id": 130,
    "typ": "saty",
    "barva": ["bila"],
    "odstin": "svetly",
    "vzor": null,
    "material": "saten",
    "styl": ["casual"],
    "sezona": ["leto"],
    "delka": "kratka",
    "strih": "slim",
    "img": "saty_saten_bila.jpg"
  },
  {
    "id": 131,
    "typ": "saty",
    "barva": ["modra"],
    "odstin": "svetly",
    "vzor": null,
    "material": "saten",
    "styl": ["casual"],
    "sezona": ["leto"],
    "delka": "kratka",
    "strih": "slim",
    "img": "saty_saten_svmodra.jpg"
  },
  {
    "id": 132,
    "typ": "saty",
    "barva": ["seda"],
    "odstin": "tmavy",
    "vzor": null,
    "material": "bavlna",
    "styl": ["casual"],
    "sezona": ["leto", "jaro", "podzim"],
    "delka": "dlouha",
    "strih": "volny",
    "img": "saty_slouhe_sede.jpg"
  },
  {
    "id": 133,
    "typ": "saty",
    "barva": ["cerna"],
    "odstin": "tmavy",
    "vzor": null,
    "material": "zerzej",
    "styl": ["spolecenske"],
    "sezona": ["leto", "jaro", "podzim", "zima"],
    "delka": "dlouha",
    "strih": "volny",
    "img": "saty_spolec.jpg"
  },
  {
    "id": 134,
    "typ": "saty",
    "barva": ["zelena"],
    "odstin": "svetly",
    "vzor": null,
    "material": "sifon",
    "styl": ["casual"],
    "sezona": ["leto"],
    "delka": "stredni",
    "strih": "volny",
    "img": "saty_svzelene_sifon.jpg"
  },
  {
    "id": 135,
    "typ": "saty",
    "barva": ["modra"],
    "odstin": "tmavy",
    "vzor": null,
    "material": "krajka",
    "styl": ["casual"],
    "sezona": ["leto"],
    "delka": "dlouha",
    "strih": "volny",
    "img": "saty_tmmodra_azura.jpg"
  },
  {
    "id": 136,
    "typ": "saty",
    "barva": ["zelena"],
    "odstin": "tmavy",
    "vzor": null,
    "material": "krajka",
    "styl": ["casual"],
    "sezona": ["leto"],
    "delka": "dlouha",
    "strih": "volny",
    "img": "saty_zelene_azura.jpg"
  },
  {
    "id": 137,
    "typ": "saty",
    "barva": ["zluta"],
    "odstin": "svetly",
    "vzor": "kvetovane",
    "material": "bavlna",
    "styl": ["casual"],
    "sezona": ["leto"],
    "delka": "dlouha",
    "strih": "volny",
    "img": "saty_zlute_kvetinove.jpg"
  },
  {
    "id": 138,
    "typ": "topy",
    "barva": ["bezova"],
    "odstin": "svetly",
    "vzor": null,
    "material": "bavlna",
    "styl": ["casual"],
    "sezona": ["leto"],
    "delka": "kratka",
    "strih": "slim",
    "img": "top_bezovy.jpg"
  },
  {
    "id": 139,
    "typ": "topy",
    "barva": ["bila"],
    "odstin": "svetly",
    "vzor": null,
    "material": "bavlna",
    "styl": ["casual"],
    "sezona": ["leto"],
    "delka": "kratka",
    "strih": "slim",
    "img": "top_bily.jpg"
  },
  {
    "id": 140,
    "typ": "topy",
    "barva": ["cerna"],
    "odstin": "tmavy",
    "vzor": null,
    "material": "krep",
    "styl": ["casual"],
    "sezona": ["leto"],
    "delka": "kratka",
    "strih": "slim",
    "img": "top_cerny.jpg"
  },
  {
    "id": 141,
    "typ": "topy",
    "barva": ["cervena"],
    "odstin": "tmavy",
    "vzor": null,
    "material": "bavlna",
    "styl": ["casual"],
    "sezona": ["leto"],
    "delka": "kratka",
    "strih": "slim",
    "img": "top_cerveny.jpg"
  },
  {
    "id": 142,
    "typ": "topy",
    "barva": ["hneda"],
    "odstin": "tmavy",
    "vzor": null,
    "material": "bavlna",
    "styl": ["casual"],
    "sezona": ["leto"],
    "delka": "kratka",
    "strih": "slim",
    "img": "top_hnedy.jpg"
  },
  {
    "id": 143,
    "typ": "topy",
    "barva": ["hneda"],
    "odstin": "tmavy",
    "vzor": null,
    "material": "bavlna",
    "styl": ["casual"],
    "sezona": ["leto"],
    "delka": "kratka",
    "strih": "slim",
    "img": "top_hnedy.jpg"
  },
  {
    "id": 144,
    "typ": "topy",
    "barva": ["modra"],
    "odstin": "tmavy",
    "vzor": null,
    "material": "bavlna",
    "styl": ["casual"],
    "sezona": ["leto"],
    "delka": "kratka",
    "strih": "slim",
    "img": "top_modry_tmavy.jpg"
  },
  {
    "id": 145,
    "typ": "topy",
    "barva": ["modra"],
    "odstin": "svetly",
    "vzor": null,
    "material": "bavlna",
    "styl": ["casual"],
    "sezona": ["leto"],
    "delka": "kratka",
    "strih": "slim",
    "img": "top_modry.jpg"
  },
  {
    "id": 146,
    "typ": "topy",
    "barva": ["bila"],
    "odstin": "svetly",
    "vzor": "pruhovane",
    "material": "bavlna",
    "styl": ["casual"],
    "sezona": ["leto"],
    "delka": "dlouha",
    "strih": "slim",
    "img": "top_pruh_dlouhe.jpg"
  },
  {
    "id": 147,
    "typ": "topy",
    "barva": ["seda"],
    "odstin": "tmavy",
    "vzor": null,
    "material": "bavlna",
    "styl": ["casual"],
    "sezona": ["leto"],
    "delka": "kratka",
    "strih": "slim",
    "img": "top_sedy.jpg"
  },
  {
    "id": 148,
    "typ": "topy",
    "barva": ["bila", "cerna"],
    "odstin": "svetly",
    "vzor": "pruhovane",
    "material": "bavlna",
    "styl": ["casual"],
    "sezona": ["leto"],
    "delka": "kratka",
    "strih": "slim",
    "img": "top_vzorovany_pruh.jpg"
  },
  {
    "id": 149,
    "typ": "topy",
    "barva": ["bila", "cerna"],
    "odstin": "svetly",
    "vzor": "zvireci",
    "material": "krep",
    "styl": ["casual"],
    "sezona": ["leto"],
    "delka": "kratka",
    "strih": "regular",
    "img": "top_vzorovany.jpg"
  },
  {
    "id": 150,
    "typ": "topy",
    "barva": ["zluta"],
    "odstin": "svetly",
    "vzor": null,
    "material": "krajka",
    "styl": ["casual"],
    "sezona": ["leto"],
    "delka": "kratka",
    "strih": "regular",
    "img": "top_zluty.jpg"
  },
  {
    "id": 151,
    "typ": "triko",
    "barva": ["vice barev"],
    "odstin": "svetly",
    "vzor": "kvetovane",
    "material": "polyester",
    "styl": ["casual"],
    "sezona": ["jaro", "podzim"],
    "delka": "kratka",
    "strih": "regular",
    "img": "rolak_kvetovany.jpg"
  },
  {
    "id": 152,
    "typ": "triko",
    "barva": ["cerna"],
    "odstin": "tmavy",
    "vzor": null,
    "material": "bavlna",
    "styl": ["sportovni"],
    "sezona": ["jaro", "leto"],
    "delka": "stredni",
    "strih": "regular",
    "img": "sportovni triko.jpg"
  },
  {
    "id": 153,
    "typ": "triko",
    "barva": ["bila"],
    "odstin": "svetly",
    "vzor": null,
    "material": "bavlna",
    "styl": ["casual"],
    "sezona": ["jaro", "leto", "podzim"],
    "delka": "stredni",
    "strih": "regular",
    "img": "triko_basic_bila.jpg"
  },
  {
    "id": 154,
    "typ": "triko",
    "barva": ["cerna"],
    "odstin": "tmavy",
    "vzor": null,
    "material": "bavlna",
    "styl": ["casual"],
    "sezona": ["jaro", "leto", "podzim"],
    "delka": "stredni",
    "strih": "regular",
    "img": "triko_basic_cerna.jpg"
  },
  {
    "id": 155,
    "typ": "triko",
    "barva": ["hneda"],
    "odstin": "tmavy",
    "vzor": null,
    "material": "bavlna",
    "styl": ["casual"],
    "sezona": ["jaro", "leto", "podzim"],
    "delka": "stredni",
    "strih": "regular",
    "img": "triko_basic_hneda.jpg"
  },
  {
    "id": 156,
    "typ": "triko",
    "barva": ["ruzova"],
    "odstin": "svetly",
    "vzor": null,
    "material": "bavlna",
    "styl": ["casual"],
    "sezona": ["jaro", "leto"],
    "delka": "stredni",
    "strih": "regular",
    "img": "triko_basic_ruzova.jpg"
  },
  {
    "id": 157,
    "typ": "triko",
    "barva": ["seda"],
    "odstin": "svetly",
    "vzor": null,
    "material": "bavlna",
    "styl": ["casual"],
    "sezona": ["jaro", "leto", "podzim"],
    "delka": "stredni",
    "strih": "regular",
    "img": "triko_basic_seda.jpg"
  },
  {
    "id": 158,
    "typ": "triko",
    "barva": ["bila"],
    "odstin": "svetly",
    "vzor": "kvetovane",
    "material": "bavlna",
    "styl": ["casual"],
    "sezona": ["jaro", "leto"],
    "delka": "stredni",
    "strih": "regular",
    "img": "triko_bile_potisk.jpg"
  },
  {
    "id": 159,
    "typ": "triko",
    "barva": ["bila"],
    "odstin": "svetly",
    "vzor": null,
    "material": "bavlna",
    "styl": ["casual"],
    "sezona": ["jaro", "leto"],
    "delka": "stredni",
    "strih": "regular",
    "img": "triko_bile.jpg"
  },
  {
    "id": 160,
    "typ": "triko",
    "barva": ["bezova"],
    "odstin": "svetly",
    "vzor": null,
    "material": "bavlna",
    "styl": ["casual"],
    "sezona": ["jaro", "podzim"],
    "delka": "stredni",
    "strih": "regular",
    "img": "triko_dlrukav_bezova.jpg"
  },
  {
    "id": 161,
    "typ": "triko",
    "barva": ["bila"],
    "odstin": "svetly",
    "vzor": null,
    "material": "bavlna",
    "styl": ["casual"],
    "sezona": ["jaro", "podzim", "zima"],
    "delka": "stredni",
    "strih": "regular",
    "img": "triko_dlrukav_bila.jpg"
  },
  {
    "id": 162,
    "typ": "triko",
    "barva": ["cerna"],
    "odstin": "tmavy",
    "vzor": null,
    "material": "bavlna",
    "styl": ["casual"],
    "sezona": ["jaro", "podzim", "zima"],
    "delka": "stredni",
    "strih": "regular",
    "img": "triko_dlrukav_cerna.jpg"
  },
  {
    "id": 163,
    "typ": "triko",
    "barva": ["cerna", "bila"],
    "odstin": "tmavy",
    "vzor": "pruhovane",
    "material": "bavlna",
    "styl": ["casual"],
    "sezona": ["jaro", "podzim", "leto"],
    "delka": "stredni",
    "strih": "regular",
    "img": "triko_polo.jpg"
  },
  {
    "id": 164,
    "typ": "triko",
    "barva": ["cervena", "bila"],
    "odstin": "tmavy",
    "vzor": "pruhovane",
    "material": "bavlna",
    "styl": ["casual"],
    "sezona": ["jaro", "podzim", "leto"],
    "delka": "stredni",
    "strih": "regular",
    "img": "triko_pruhovane.jpg"
  },
  {
    "id": 165,
    "typ": "triko",
    "barva": ["modra"],
    "odstin": "tmavy",
    "vzor": null,
    "material": "bavlna",
    "styl": ["casual"],
    "sezona": ["jaro", "podzim", "leto"],
    "delka": "stredni",
    "strih": "regular",
    "img": "triko_tmmodra.jpg"
  },
  {
    "id": 166,
    "typ": "kosile",
    "barva": ["modra"],
    "odstin": "tmavy",
    "vzor": "pruhovane",
    "material": "denim",
    "styl": ["casual"],
    "sezona": ["jaro", "podzim"],
    "delka": "stredni",
    "strih": "volny",
    "img": "košile_denim pruhy.jpg"
  },
  {
    "id": 167,
    "typ": "kosile",
    "barva": ["modra"],
    "odstin": "tmavy",
    "vzor": null,
    "material": "denim",
    "styl": ["casual"],
    "sezona": ["jaro", "leto", "podzim"],
    "delka": "dlouha",
    "strih": "volny",
    "img": "kosile_denim_tmava.jpg"
  },

  {
    "id": 168,
    "typ": "triko",
    "barva": ["oranzova"],
    "odstin": null,
    "vzor": null,
    "material": "krep",
    "styl": ["casual"],
    "sezona": ["jaro", "leto"],
    "delka": "kratka",
    "strih": null,
    "img": "triko_oranzova_krep.jpg"
  },

  {
    "id": 169,
    "typ": "triko",
    "barva": ["oranzova"],
    "odstin": "neutralni",
    "vzor": null,
    "material": "bavlna",
    "styl": ["casual"],
    "sezona": ["podzim", "zima"],
    "delka": "dlouha",
    "strih": "regular",
    "img": "triko_dlouhe_oranz.jpg"
  },

  {
    "id": 170,
    "typ": "saty",
    "barva": ["oranzova"],
    "odstin": "tmavy",
    "vzor": null,
    "material": "zerzej",
    "styl": ["casual"],
    "sezona": ["leto"],
    "delka": "dlouha",
    "strih": "volny",
    "img": "saty_zerzej_oranzova.jpg"
  },

  {
    "id": 171,
    "typ": "saty",
    "barva": ["modra"],
    "odstin": "tmavy",
    "vzor": null,
    "material": "bavlna",
    "styl": ["casual"],
    "sezona": ["leto"],
    "delka": "dlouha",
    "strih": "volny",
    "img": "overal_modry.jpg"
  },

  {
    "id": 172,
    "typ": "saty",
    "barva": ["seda"],
    "odstin": "svetly",
    "vzor": null,
    "material": "plise",
    "styl": ["casual", "spolecenske", "formalni"],
    "sezona": ["jaro", "leto", "podzim"],
    "delka": "dlouha",
    "strih": null,
    "img": "šaty_společ_plise.jpg"
  },

  {
    "id": 173,
    "typ": "saty",
    "barva": ["cerna"],
    "odstin": null,
    "vzor": null,
    "material": null,
    "styl": ["formalni", "spolecenske"],
    "sezona": ["leto", "podzim", "zima", "jaro"],
    "delka": "dlouha",
    "strih": "regular",
    "img": "saty_spolecenske_cerne.jpg"
  },

  {
    "id": 174,
    "typ": "saty",
    "barva": ["hneda"],
    "odstin": "tmavy",
    "vzor": null,
    "material": "saten",
    "styl": ["casual", "spolecenske", "formalni"],
    "sezona": ["jaro", "leto", "podzim", "zima"],
    "delka": "dlouha",
    "strih": "regular",
    "img": "saty_spolecenske_hneda.jpg"
  },

  {
    "id": 175,
    "typ": "kratasy",
    "barva": ["zelena"],
    "odstin": "svetly",
    "vzor": null,
    "material": "polyester",
    "styl": ["sportovni"],
    "sezona": null,
    "delka": "kratka",
    "strih": "slim",
    "img": "kratasy_sport_svzelena.jpg"
  },

  {
    "id": 176,
    "typ": "kalhoty",
    "barva": ["zluta"],
    "odstin": "svetly",
    "vzor": null,
    "material": "polyester",
    "styl": ["sportovni"],
    "sezona": null,
    "delka": "dlouha",
    "strih": "slim",
    "img": "kalhoty_zluta_sport.jpg"
  },

  {
    "id": 177,
    "typ": "kalhoty",
    "barva": ["ruzova"],
    "odstin": "svetly",
    "vzor": null,
    "material": "polyester",
    "styl": ["sportovni"],
    "sezona": null,
    "delka": "dlouha",
    "strih": "slim",
    "img": "kalhoty_sport_ruzova.jpg"
  },

  {
    "id": 178,
    "typ": "svetr",
    "barva": ["bila"],
    "odstin": "tmavy",
    "vzor": null,
    "material": null,
    "styl": ["sportovni"],
    "sezona": null,
    "delka": "dlouha",
    "strih": "regular",
    "img": "mikina_bila_sport.jpg"
  },

  {
    "id": 179,
    "typ": "topy",
    "barva": ["bila"],
    "odstin": null,
    "vzor": null,
    "material": "polyester",
    "styl": ["sportovni"],
    "sezona": null,
    "delka": "kratka",
    "strih": "regular",
    "img": "tilko_bila_sport.jpg"
  },

  {
    "id": 180,
    "typ": "halenka",
    "barva": ["zluta"],
    "odstin": null,
    "vzor": null,
    "material": null,
    "styl": ["casual"],
    "sezona": ["leto"],
    "delka": "kratka",
    "strih": "regular",
    "img": "halenka_zluta.jpg"
  },

  {
    "id": 181,
    "typ": "halenka",
    "barva": ["bezova"],
    "odstin": "svetly",
    "vzor": null,
    "material": "krajka",
    "styl": ["casual"],
    "sezona": ["leto"],
    "delka": null,
    "strih": "volny",
    "img": "halenka_krajka_bezova.jpg"
  },

  {
    "id": 182,
    "typ": "kalhoty",
    "barva": ["ruzova"],
    "odstin": "svetly",
    "vzor": null,
    "material": null,
    "styl": ["casual"],
    "sezona": ["leto", "jaro", "leto"],
    "delka": null,
    "strih": "volny",
    "img": "kalhoty_cargo_ruzova.jpg"
  },
  {
    "id": 183,
    "typ": "kalhoty",
    "barva": ["cerna"],
    "odstin": null,
    "vzor": null,
    "material": null,
    "styl": ["formalni"],
    "sezona": ["leto", "jaro", "leto", "zima"],
    "delka": null,
    "strih": "slim",
    "img": "kalhoty_formalni_slim.jpg"
  },
  {
    "id": 184,
    "typ": "kalhoty",
    "barva": ["zelena"],
    "odstin": null,
    "vzor": null,
    "material": null,
    "styl": ["casual"],
    "sezona": ["leto", "jaro", "podzim"],
    "delka": "kratka",
    "strih": "regular",
    "img": "kalhoty_kratke_zelene.jpg"
  },
  {
    "id": 185,
    "typ": "kalhoty",
    "barva": ["bezova"],
    "odstin": "tmavy",
    "vzor": null,
    "material": "len",
    "styl": ["casual"],
    "sezona": ["leto", "jaro"],
    "delka": "dlouha",
    "strih": "volny",
    "img": "kalhoty_lnene_volne.jpg"
  },

  {
    "id": 186,
    "typ": "kalhoty",
    "barva": ["seda"],
    "odstin": null,
    "vzor": "kostkovane",
    "material": null,
    "styl": ["casual", "formalni"],
    "sezona": ["leto", "jaro"],
    "delka": "dlouha",
    "strih": "slim",
    "img": "kalhoty_kostka_slim.jpg"
  },
  {
    "id": 187,
    "typ": "kosile",
    "barva": ["modra"],
    "odstin": "tmavy",
    "vzor": null,
    "material": "krajka",
    "styl": ["casual"],
    "sezona": ["jaro", "leto"],
    "delka": "stredni",
    "strih": "volny",
    "img": "kosile_tmmodra_azura.jpg"
  }
]
